setup.py
arix_distribution/Binomialdistribution.py
arix_distribution/Gaussiandistribution.py
arix_distribution/Generaldistribution.py
arix_distribution/__init__.py
arix_distribution.egg-info/PKG-INFO
arix_distribution.egg-info/SOURCES.txt
arix_distribution.egg-info/dependency_links.txt
arix_distribution.egg-info/not-zip-safe
arix_distribution.egg-info/top_level.txt