Metadata-Version: 1.0
Name: arix-distribution
Version: 1.1
Summary: Gaussian and Binomial distributions
Home-page: UNKNOWN
Author: Sarthak Pol
Author-email: sarthakpol711@gmail.com
License: UNKNOWN
Platform: UNKNOWN
